gh_scoped_creds/__init__.py
gh_scoped_creds-4.1.dist-info/LICENSE
gh_scoped_creds-4.1.dist-info/METADATA
gh_scoped_creds-4.1.dist-info/WHEEL
gh_scoped_creds-4.1.dist-info/entry_points.txt
gh_scoped_creds-4.1.dist-info/top_level.txt
gh_scoped_creds-4.1.dist-info/RECORD
