Metadata-Version: 2.1
Name: gh-scoped-creds
Version: 4.1
Summary: Temporary, well scoped credentials for pushing to GitHub
Home-page: https://github.com/yuvipanda/gh-scoped-creds
Author: Yuvi Panda
Author-email: yuvipanda@gmail.com
License: 3-clause BSD
Platform: any
License-File: LICENSE
